lightridge/__init__.py
lightridge/data.py
lightridge/get_h.py
lightridge/laser.py
lightridge/layers.py
lightridge/models.py
lightridge/setup.py
lightridge/utils.py
lightridge-0.2.2.dist-info/LICENSE
lightridge-0.2.2.dist-info/METADATA
lightridge-0.2.2.dist-info/WHEEL
lightridge-0.2.2.dist-info/top_level.txt
lightridge-0.2.2.dist-info/RECORD
