Metadata-Version: 2.1
Name: lightridge
Version: 0.2.2
Summary: LightRidge — An Open-Source Hardware Project for Optical AI!
Home-page: https://lightridge.github.io/lightridge/
Author: Yingjie Li, Cunxi Yu (University of Maryland, College Park)
Author-email: yingjiel@umd.edu
License: LICENSE
Project-URL: Bug Tracker, https://lightridge.github.io/lightridge/
Platform: UNKNOWN
Classifier: Programming Language :: Python :: 3
Classifier: License :: OSI Approved :: MIT License
Classifier: Operating System :: OS Independent
Requires-Python: >=3.6
Requires-Dist: torch (>=1.12.0)
Requires-Dist: torchvision (>=0.13.0)
Requires-Dist: setuptools (>=42)
Requires-Dist: pandas
Requires-Dist: tqdm
Requires-Dist: lightpipes
